{
	"configurations" : 
	[
		{
			"directories" : 
			[
				{
					"build" : ".",
					"jsonFile" : "directory-.-Debug-f5ebdc15457944623624.json",
					"minimumCMakeVersion" : 
					{
						"string" : "3.27"
					},
					"projectIndex" : 0,
					"source" : ".",
					"targetIndexes" : 
					[
						0,
						1
					]
				}
			],
			"name" : "Debug",
			"projects" : 
			[
				{
					"directoryIndexes" : 
					[
						0
					],
					"name" : "cse224",
					"targetIndexes" : 
					[
						0,
						1
					]
				}
			],
			"targets" : 
			[
				{
					"directoryIndex" : 0,
					"id" : "cse224::@6890427a1f51a3e7e1df",
					"jsonFile" : "target-cse224-Debug-774a75cceb46bf3dcdd1.json",
					"name" : "cse224",
					"projectIndex" : 0
				},
				{
					"directoryIndex" : 0,
					"id" : "lab1::@6890427a1f51a3e7e1df",
					"jsonFile" : "target-lab1-Debug-e1543a1ab7da05e9c29a.json",
					"name" : "lab1",
					"projectIndex" : 0
				}
			]
		}
	],
	"kind" : "codemodel",
	"paths" : 
	{
		"build" : "/Users/woliul/CLionProjects/cse224/cmake-build-debug",
		"source" : "/Users/woliul/CLionProjects/cse224"
	},
	"version" : 
	{
		"major" : 2,
		"minor" : 6
	}
}
